CampCoin-0.0.6.dist-info/METADATA
CampCoin-0.0.6.dist-info/RECORD
CampCoin-0.0.6.dist-info/WHEEL
CampCoin-0.0.6.dist-info/top_level.txt
campcoin-api/__init__.py
campcoin-api/block.py
campcoin-api/campcoin.py
campcoin-api/transaction.py
campcoin_api/__init__.py
campcoin_api/block.py
campcoin_api/campcoin.py
campcoin_api/transaction.py
lib/__init__.py
lib/keys.py
lib/prefix.py
