Metadata-Version: 2.1
Name: CampCoin
Version: 0.0.6
Summary: A Computer Camp Cryptocurrency
Home-page: https://github.com/compcamps/py-blockchain
Author: Taylor Petrychyn
Author-email: compcamps@gmail.com
License: UNKNOWN
Platform: UNKNOWN
Classifier: Programming Language :: Python :: 3
Classifier: License :: OSI Approved :: MIT License
Classifier: Operating System :: OS Independent
